{
  "160": "https://tv.arectv34.sbs/live/pl1.m3u8",
  "157": "https://tv.arectv34.sbs/live/tabi.m3u8",
  "149": "https://bs.arectv33.sbs/static/bs1.m3u8",
  "148": "https://bs.arectv33.sbs/static/bs2.m3u8",
  "147": "https://bs.arectv33.sbs/static/bs3.m3u8",
  "146": "https://bs.arectv33.sbs/static/bs4.m3u8",
  "145": "https://bs.arectv33.sbs/static/bs5.m3u8",
  "144": "https://tv.arectv34.sbs/live/bm1.m3u8",
  "142": "https://tv.arectv34.sbs/live/bm2.m3u8",
  "141": "https://bs.arectv33.sbs/static/ss11.m3u8",
  "140": "https://bs.arectv33.sbs/static/ss2.m3u8",
  "139": "https://tv.arectv34.sbs/live/smart1.m3u8",
  "138": "https://tv.arectv34.sbs/live/smart2.m3u8",
  "137": "https://tv.arectv34.sbs/live/euro1.m3u8",
  "135": "https://tv.arectv34.sbs/live/euro2.m3u8",
  "134": "https://tv.arectv34.sbs/live/t1.m3u8",
  "133": "https://tv.arectv34.sbs/live/t2.m3u8",
  "132": "https://tv.arectv34.sbs/live/t3.m3u8",
  "130": "https://tv.arectv34.sbs/live/aspor.m3u8",
  "129": "https://owifavo5.rocketcdn.com/gstv/gstv.smil/chunklist_b1828000_sltur.m3u8",
  "128": "https://1hskrdto.rocketcdn.com/fenerbahcetv.smil/playlist.m3u8",
  "127": "https://bs.arectv33.sbs/list/yayinnbatv.m3u8",
  "126": "https://tv.arectv34.sbs/live/fight.m3u8",
  "122": "https://live.sportstv.com.tr/hls/low/sportstv.m3u8",
  "113": "https://dogus-live.daioncdn.net/startv/startv.m3u8",
  "112": "https://demiroren-live.daioncdn.net/kanald/kanald.m3u8",
  "111": "https://ciner-live.daioncdn.net/showtv/showtv.m3u8",
  "110": "https://tv.arectv34.sbs/live/atv.m3u8",
  "109": "https://tv8-live.daioncdn.net/tv8/tv8.m3u8",
  "108": "https://tv.arectv34.sbs/live/tv85.m3u8",
  "107": "https://uycyyuuzyh.turknet.ercdn.net/nphindgytw/nowtv/nowtv.m3u8",
  "106": "https://kanal7-live.daioncdn.net/kanal7/kanal7.m3u8",
  "105": "https://beyaztv-live.daioncdn.net/beyaztv/beyaztv.m3u8",
  "103": "https://demiroren-live.daioncdn.net/teve2/teve2.m3u8",
  "102": "https://tv-trthaber.medya.trt.com.tr/master_720.m3u8",
  "101": "https://ciner-live.daioncdn.net/haberturktv/haberturktv.m3u8",
  "100": "https://tv.arectv34.sbs/live/ahaber.m3u8",
  "99": "https://tv.arectv34.sbs/live/cnnturk.m3u8",
  "98": "https://dogus-live.daioncdn.net/ntv/ntv.m3u8",
  "97": "https://tv.ensonhaber.com/tv24/tv24.m3u8",
  "96": "https://ciner.daioncdn.net/bloomberght/bloomberght.m3u8",
  "95": "https://halktv-live.daioncdn.net/halktv/halktv.m3u8",
  "94": "https://tv.ensonhaber.com/haberglobal/haberglobal.m3u8",
  "93": "https://tgrthaber-live.daioncdn.net/tgrthaber/tgrthaber.m3u8",
  "89": "https://saran-live.ercdn.net/natgeohd/index.m3u8",
  "88": "https://saran-live.ercdn.net/natgeowild/index.m3u8",
  "87": "https://tv.arectv34.sbs/live/history.m3u8",
  "86": "https://tv.arectv34.sbs/live/bbc.m3u8",
  "85": "https://tv.arectv34.sbs/live/tarihtv.m3u8",
  "84": "https://tv.arectv34.sbs/live/docubox.m3u8",
  "83": "https://dogus-live.daioncdn.net/tlc/tlc.m3u8",
  "81": "https://dogus-live.daioncdn.net/dmax/dmax.m3u8",
  "80": "https://tv.arectv34.sbs/live/yaban.m3u8",
  "79": "https://tv.arectv34.sbs/live/discovery.m3u8",
  "78": "https://tv.arectv34.sbs/live/discs.m3u8",
  "77": "https://tv-trtbelgesel.medya.trt.com.tr/master.m3u8",
  "76": "https://tv.arectv34.sbs/live/bsaction1.m3u8",
  "75": "https://tv.arectv34.sbs/live/bsturk.m3u8",
  "74": "https://tv.arectv34.sbs/live/bsfamily.m3u8",
  "72": "https://tv.arectv34.sbs/live/bsstars.m3u8",
  "71": "https://tv.arectv34.sbs/live/bspremier1.m3u8",
  "70": "https://tv.arectv34.sbs/live/box1.m3u8",
  "69": "https://tv.arectv34.sbs/live/box2.m3u8",
  "68": "https://tv.arectv34.sbs/live/box3.m3u8",
  "67": "https://tv.arectv34.sbs/live/mvturk.m3u8",
  "65": "https://saran-live.ercdn.net/fx/index.m3u8",
  "61": "https://tv.arectv34.sbs/live/sinema.m3u8",
  "60": "https://tv.arectv34.sbs/live/sinema2.m3u8",
  "59": "https://tv.arectv34.sbs/live/sinemaaksiyon2.m3u8",
  "57": "https://tv.arectv34.sbs/live/sinemakomedi.m3u8",
  "56": "https://tv.arectv34.sbs/live/sinemayerli.m3u8",
  "55": "https://tv.arectv34.sbs/live/sinemaaile.m3u8",
  "53": "https://tv.arectv34.sbs/live/sinema1001.m3u8",
  "52": "https://tv.arectv34.sbs/live/sinema1002.m3u8",
  "51": "https://live.duhnet.tv/S2/HLS_LIVE/dreamturknp/playlist.m3u8",
  "50": "https://tv-trtmuzik.medya.trt.com.tr/master.m3u8",
  "49": "https://live.artidijitalmedya.com/artidijital_powerturktv/powerturktv/playlist.m3u8",
  "48": "https://live.artidijitalmedya.com/artidijital_powertv/powertv/playlist.m3u8",
  "47": "https://b01c02nl.mediatriple.net/videoonlylive/mtkgeuihrlfwlive/broadcast_5c9e17cd59e8b.smil/playlist.m3u8",
  "46": "https://b01c02nl.mediatriple.net/videoonlylive/mtkgeuihrlfwlive/broadcast_5c9e187770143.smil/playlist.m3u8",
  "36": "https://tv.arectv34.sbs/live/cartoonnetwork.m3u8",
  "35": "http://fl1.moveonjoy.com/NICKELODEON/index.m3u8",
  "34": "https://tv.arectv34.sbs/live/davinci.m3u8",
  "33": "https://saran-live.ercdn.net/disneyjunior/index.m3u8",
  "32": "https://tv.arectv34.sbs/live/lovenature.m3u8",
  "30": "https://tv.arectv34.sbs/live/viasathistory.m3u8",
  "28": "https://kontv.blutv.com/blutv_kontv2/live_720p2000000kbps/index.m3u8",
  "26": "https://ythls.kekikakademi.org/youtube/channel/UCOulx_rep5O4i9y6AyDqVvw.m3u8",
  "25": "https://tv.ensonhaber.com/benguturk/benguturk.m3u8",
  "24": "https://tv100-live.daioncdn.net/tv100/tv100_1080p.m3u8",
  "22": "https://tv-trt2.medya.trt.com.tr/master.m3u8",
  "18": "https://trtturk.blutv.com/blutv_trtturk2/live_720p2000000kbps/index.m3u8",
  "17": "https://tv-trtavaz.medya.trt.com.tr/master.m3u8",
  "13": "https://tv.arectv34.sbs/live/t4.m3u8",
  "10": "https://fashiontv-fashiontv-1-eu.rakuten.wurl.tv/playlist.m3u8"
}